iiko_sdk/__init__.py
iiko_sdk/gateways/__init__.py
iiko_sdk/gateways/iiko_utils.py
iiko_sdk/gateways/transformers.py
iiko_sdk/gateways/authorization/__init__.py
iiko_sdk/gateways/authorization/v1/__init__.py
iiko_sdk/gateways/authorization/v1/client.py
iiko_sdk/gateways/general/__init__.py
iiko_sdk/gateways/general/v1/__init__.py
iiko_sdk/gateways/general/v1/client.py
iiko_sdk/gateways/general/v2/__init__.py
iiko_sdk/gateways/general/v2/client.py
iiko_sdk/gateways/orders/__init__.py
iiko_sdk/gateways/orders/enums.py
iiko_sdk/gateways/orders/v1/__init__.py
iiko_sdk/gateways/orders/v1/client.py
iiko_sdk/gateways/reserves/__init__.py
iiko_sdk/gateways/reserves/client.py
iiko_sdk-0.0.8.dist-info/METADATA
iiko_sdk-0.0.8.dist-info/WHEEL
iiko_sdk-0.0.8.dist-info/top_level.txt
iiko_sdk-0.0.8.dist-info/RECORD
