Metadata-Version: 2.4
Name: iiko-sdk
Version: 0.0.8
Summary: IIKO Cloud SDK API
Author: Anton Gorinenko
Author-email: anton.gorinenko@gmail.com
Keywords: python,utils,http
Classifier: Programming Language :: Python :: 3.13
Classifier: Operating System :: OS Independent
Requires-Python: >=3.13
Requires-Dist: aiohttp>=3.11
Requires-Dist: http-misc>=1.0.4
Provides-Extra: test
Requires-Dist: pytest; extra == "test"
Requires-Dist: python-dotenv; extra == "test"
Requires-Dist: envparse; extra == "test"
Requires-Dist: pytest-asyncio; extra == "test"
Dynamic: author
Dynamic: author-email
Dynamic: classifier
Dynamic: description-content-type
Dynamic: keywords
Dynamic: provides-extra
Dynamic: requires-dist
Dynamic: requires-python
Dynamic: summary
